enigmapython/Alphabets.py
enigmapython/Clonable.py
enigmapython/DynamicTurnoverRotor.py
enigmapython/Enigma.py
enigmapython/EnigmaB_A133.py
enigmapython/EnigmaB_A133Etw.py
enigmapython/EnigmaB_A133RotorI.py
enigmapython/EnigmaB_A133RotorII.py
enigmapython/EnigmaB_A133RotorIII.py
enigmapython/EnigmaD.py
enigmapython/EnigmaDRotorI.py
enigmapython/EnigmaDRotorII.py
enigmapython/EnigmaDRotorIII.py
enigmapython/EnigmaI.py
enigmapython/EnigmaINorway.py
enigmapython/EnigmaINorwayRotorI.py
enigmapython/EnigmaINorwayRotorII.py
enigmapython/EnigmaINorwayRotorIII.py
enigmapython/EnigmaINorwayRotorIV.py
enigmapython/EnigmaINorwayRotorV.py
enigmapython/EnigmaIRotorI.py
enigmapython/EnigmaIRotorII.py
enigmapython/EnigmaIRotorIII.py
enigmapython/EnigmaIRotorIV.py
enigmapython/EnigmaIRotorV.py
enigmapython/EnigmaISonder.py
enigmapython/EnigmaISonderRotorI.py
enigmapython/EnigmaISonderRotorII.py
enigmapython/EnigmaISonderRotorIII.py
enigmapython/EnigmaK.py
enigmapython/EnigmaKRotorI.py
enigmapython/EnigmaKRotorII.py
enigmapython/EnigmaKRotorIII.py
enigmapython/EnigmaM3.py
enigmapython/EnigmaM3RotorI.py
enigmapython/EnigmaM3RotorII.py
enigmapython/EnigmaM3RotorIII.py
enigmapython/EnigmaM3RotorIV.py
enigmapython/EnigmaM3RotorV.py
enigmapython/EnigmaM3RotorVI.py
enigmapython/EnigmaM3RotorVII.py
enigmapython/EnigmaM3RotorVIII.py
enigmapython/EnigmaM4.py
enigmapython/EnigmaM4RotorBeta.py
enigmapython/EnigmaM4RotorGamma.py
enigmapython/EnigmaM4RotorI.py
enigmapython/EnigmaM4RotorII.py
enigmapython/EnigmaM4RotorIII.py
enigmapython/EnigmaM4RotorIV.py
enigmapython/EnigmaM4RotorV.py
enigmapython/EnigmaM4RotorVI.py
enigmapython/EnigmaM4RotorVII.py
enigmapython/EnigmaM4RotorVIII.py
enigmapython/EnigmaZ.py
enigmapython/EnigmaZEtw.py
enigmapython/EnigmaZRotorI.py
enigmapython/EnigmaZRotorII.py
enigmapython/EnigmaZRotorIII.py
enigmapython/Etw.py
enigmapython/EtwPassthrough.py
enigmapython/EtwQWERTZ.py
enigmapython/Journaled.py
enigmapython/Observable.py
enigmapython/Observer.py
enigmapython-3.0.1.dist-info/METADATA
enigmapython-3.0.1.dist-info/WHEEL
enigmapython-3.0.1.dist-info/top_level.txt
enigmapython-3.0.1.dist-info/RECORD
