Metadata-Version: 2.4
Name: enigmapython
Version: 3.0.1
Summary: A simple yet faithful library to emulate different Enigma machines models using Python
Home-page: https://github.com/denismaggior8/enigma-python
Author: Denis Maggiorotto
License: MIT
Classifier: Programming Language :: Python :: 3
Classifier: Operating System :: OS Independent
Classifier: License :: OSI Approved :: MIT License
Dynamic: author
Dynamic: classifier
Dynamic: description
Dynamic: description-content-type
Dynamic: home-page
Dynamic: license
Dynamic: summary
